jupydrive_s3/__init__.py
jupydrive_s3/_version.py
jupydrive_s3-0.1.0.data/data/share/jupyter/labextensions/jupydrive-s3/package.json
jupydrive_s3-0.1.0.data/data/share/jupyter/labextensions/jupydrive-s3/schemas/jupydrive-s3/auth-file-browser.json
jupydrive_s3-0.1.0.data/data/share/jupyter/labextensions/jupydrive-s3/schemas/jupydrive-s3/file-browser-toolbar.json
jupydrive_s3-0.1.0.data/data/share/jupyter/labextensions/jupydrive-s3/schemas/jupydrive-s3/package.json.orig
jupydrive_s3-0.1.0.data/data/share/jupyter/labextensions/jupydrive-s3/static/249.f1a0dfa70f0abaff34d2.js
jupydrive_s3-0.1.0.data/data/share/jupyter/labextensions/jupydrive-s3/static/313.edd612caa982524216f7.js
jupydrive_s3-0.1.0.data/data/share/jupyter/labextensions/jupydrive-s3/static/52.6379e0503eed5f9af25e.js
jupydrive_s3-0.1.0.data/data/share/jupyter/labextensions/jupydrive-s3/static/694.edd612caa982524216f7.js
jupydrive_s3-0.1.0.data/data/share/jupyter/labextensions/jupydrive-s3/static/728.ce82e6e030c720812b15.js
jupydrive_s3-0.1.0.data/data/share/jupyter/labextensions/jupydrive-s3/static/732.9359fc93675a8f862db2.js
jupydrive_s3-0.1.0.data/data/share/jupyter/labextensions/jupydrive-s3/static/956.698b70cd333da8a54755.js
jupydrive_s3-0.1.0.data/data/share/jupyter/labextensions/jupydrive-s3/static/remoteEntry.20b5a0279ea394f88afa.js
jupydrive_s3-0.1.0.data/data/share/jupyter/labextensions/jupydrive-s3/static/style.js
jupydrive_s3-0.1.0.data/data/share/jupyter/labextensions/jupydrive-s3/static/third-party-licenses.json
jupydrive_s3-0.1.0.data/data/share/jupyter/labextensions/jupydrive-s3/install.json
jupydrive_s3-0.1.0.dist-info/METADATA
jupydrive_s3-0.1.0.dist-info/WHEEL
jupydrive_s3-0.1.0.dist-info/licenses/LICENSE
jupydrive_s3-0.1.0.dist-info/RECORD
