Metadata-Version: 2.4
Name: jupydrive_s3
Version: 0.1.0
Dynamic: Keywords
Summary: A JupyterLab extension which enables client-side drives access.
Project-URL: Homepage, https://github.com/QuantStack/jupydrive-s3
Project-URL: Bug Tracker, https://github.com/QuantStack/jupydrive-s3/issues
Project-URL: Repository, https://github.com/QuantStack/jupydrive-s3.git
Author-email: QuantStack <denisa.checiu@quantstack.net>
License: BSD 3-Clause License
License-File: LICENSE
Classifier: Framework :: Jupyter
Classifier: Framework :: Jupyter :: JupyterLab
Classifier: Framework :: Jupyter :: JupyterLab :: 4
Classifier: Framework :: Jupyter :: JupyterLab :: Extensions
Classifier: Framework :: Jupyter :: JupyterLab :: Extensions :: Prebuilt
Classifier: License :: OSI Approved :: BSD License
Classifier: Programming Language :: Python
Classifier: Programming Language :: Python :: 3
Classifier: Programming Language :: Python :: 3.8
Classifier: Programming Language :: Python :: 3.9
Classifier: Programming Language :: Python :: 3.10
Classifier: Programming Language :: Python :: 3.11
Classifier: Programming Language :: Python :: 3.12
Requires-Python: >=3.8
Requires-Dist: jupyter-secrets-manager<0.5,>=0.4
